MANIFEST.in
README.md
setup.cfg
setup.py
lingfeat/__init__.py
lingfeat/extractor.py
lingfeat/utils.py
lingfeat.egg-info/PKG-INFO
lingfeat.egg-info/SOURCES.txt
lingfeat.egg-info/dependency_links.txt
lingfeat.egg-info/requires.txt
lingfeat.egg-info/top_level.txt
lingfeat/_AdvancedSemantic/OSKF.py
lingfeat/_AdvancedSemantic/WBKF.py
lingfeat/_AdvancedSemantic/WoKF.py
lingfeat/_AdvancedSemantic/__init__.py
lingfeat/_AdvancedSemantic/model/__init__.py
lingfeat/_AdvancedSemantic/model/enwiki100
lingfeat/_AdvancedSemantic/model/enwiki100.expElogbeta.npy
lingfeat/_AdvancedSemantic/model/enwiki100.state
lingfeat/_AdvancedSemantic/model/enwiki150
lingfeat/_AdvancedSemantic/model/enwiki150.expElogbeta.npy
lingfeat/_AdvancedSemantic/model/enwiki150.state
lingfeat/_AdvancedSemantic/model/enwiki150.state.sstats.npy
lingfeat/_AdvancedSemantic/model/enwiki200
lingfeat/_AdvancedSemantic/model/enwiki200.expElogbeta.npy
lingfeat/_AdvancedSemantic/model/enwiki200.state
lingfeat/_AdvancedSemantic/model/enwiki200.state.sstats.npy
lingfeat/_AdvancedSemantic/model/enwiki50
lingfeat/_AdvancedSemantic/model/enwiki50.expElogbeta.npy
lingfeat/_AdvancedSemantic/model/enwiki50.state
lingfeat/_AdvancedSemantic/model/onestop100
lingfeat/_AdvancedSemantic/model/onestop100.expElogbeta.npy
lingfeat/_AdvancedSemantic/model/onestop100.state
lingfeat/_AdvancedSemantic/model/onestop150
lingfeat/_AdvancedSemantic/model/onestop150.expElogbeta.npy
lingfeat/_AdvancedSemantic/model/onestop150.state
lingfeat/_AdvancedSemantic/model/onestop200
lingfeat/_AdvancedSemantic/model/onestop200.expElogbeta.npy
lingfeat/_AdvancedSemantic/model/onestop200.state
lingfeat/_AdvancedSemantic/model/onestop50
lingfeat/_AdvancedSemantic/model/onestop50.expElogbeta.npy
lingfeat/_AdvancedSemantic/model/onestop50.state
lingfeat/_AdvancedSemantic/model/weebit100
lingfeat/_AdvancedSemantic/model/weebit100.expElogbeta.npy
lingfeat/_AdvancedSemantic/model/weebit100.state
lingfeat/_AdvancedSemantic/model/weebit150
lingfeat/_AdvancedSemantic/model/weebit150.expElogbeta.npy
lingfeat/_AdvancedSemantic/model/weebit150.state
lingfeat/_AdvancedSemantic/model/weebit200
